alembic_api/__init__.py
alembic_api/cfg.py
alembic_api/client.py
alembic_api/decorators.py
alembic_api/server.py
alembic_api/utils.py
alembic_api-0.0.5.dist-info/METADATA
alembic_api-0.0.5.dist-info/WHEEL
alembic_api-0.0.5.dist-info/RECORD
